[
  {
    "rowid": "1",
    "event_id": 769,
    "eventname": "2023 Surf-Forum-One-Hour Challenge 2023",
    "speed": 46.677808000000006,
    "type": "speed_hour",
    "username": "Andr\u00e9 Menz",
    "ageclass": "Grand Master (51-60)",
    "weightclass": "81-90",
    "sexe": "Men",
    "spotname": "Wolderwijd - Strand Horst",
    "sessionboard": "PATRIK Slalom 115",
    "sessionsail": "Severne Overdrive M4  7.0",
    "sessionfin": "C-Fins 6.0  37",
    "sessionurl": "https://www.gps-speedsurfing.com/?mnu=user&val=418381&uid=26921"
  },
  {
    "rowid": "2",
    "event_id": 769,
    "eventname": "2023 Surf-Forum-One-Hour Challenge 2023",
    "speed": 46.261108,
    "type": "speed_hour",
    "username": "Boris Mueller",
    "ageclass": "Master (36-50)",
    "weightclass": "71-80",
    "sexe": "Men",
    "spotname": "Grevelingenmeer - Zonnemaire",
    "sessionboard": "JP Slalom 62 Pro Edition",
    "sessionsail": "Duotone Warp  6.2",
    "sessionfin": "MS-Fins R2  32",
    "sessionurl": "https://www.gps-speedsurfing.com/?mnu=user&val=417292&uid=24640"
  },
  {
    "rowid": "3",
    "event_id": 769,
    "eventname": "2023 Surf-Forum-One-Hour Challenge 2023",
    "speed": 45.666616000000005,
    "type": "speed_hour",
    "username": "Christian Hirschberg",
    "ageclass": "Grand Master (51-60)",
    "weightclass": "71-80",
    "sexe": "Men",
    "spotname": "Grevelingenmeer - Zonnemaire",
    "sessionboard": "Starboard iSonic 63 Carbon Reflex",
    "sessionsail": "Point-7 AC1  6.2",
    "sessionfin": "MS-Fins X7 S  32",
    "sessionurl": "https://www.gps-speedsurfing.com/?mnu=user&val=402404&uid=24389"
  },
  {
    "rowid": "4",
    "event_id": 769,
    "eventname": "2023 Surf-Forum-One-Hour Challenge 2023",
    "speed": 45.32770000000001,
    "type": "speed_hour",
    "username": "Dominik Kocholl",
    "ageclass": "Master (36-50)",
    "weightclass": "81-90",
    "sexe": "Men",
    "spotname": "Gruissan",
    "sessionboard": "Fanatic  FALCON   115 TE 2021",
    "sessionsail": "Duotone Warp-Fin 20.21  7.7",
    "sessionfin": "NoLo NoLo 6  365",
    "sessionurl": "https://www.gps-speedsurfing.com/?mnu=user&val=416669&uid=26794"
  },
  {
    "rowid": "5",
    "event_id": 769,
    "eventname": "2023 Surf-Forum-One-Hour Challenge 2023",
    "speed": 45.116572000000005,
    "type": "speed_hour",
    "username": "Carsten Hanke",
    "ageclass": "Grand Master (51-60)",
    "weightclass": "71-80",
    "sexe": "Men",
    "spotname": "IJsselmeer - Makkum",
    "sessionboard": "PATRIK Slalom 100",
    "sessionsail": "Patrik Race+  7.0",
    "sessionfin": "Feine Finnen Biting Beast 2.0  33",
    "sessionurl": "https://www.gps-speedsurfing.com/?mnu=user&val=413581&uid=5456"
  },
  {
    "rowid": "6",
    "event_id": 769,
    "eventname": "2023 Surf-Forum-One-Hour Challenge 2023",
    "speed": 44.088712,
    "type": "speed_hour",
    "username": "Thomas Moldenhauer",
    "ageclass": "Grand Master (51-60)",
    "weightclass": "81-90",
    "sexe": "Men",
    "spotname": "Grevelingenmeer - Zonnemaire",
    "sessionboard": "AV Modena Slalom 60",
    "sessionsail": "Neilpryde RS:RACING EVOXIII  5.8",
    "sessionfin": "NoLo 6  30",
    "sessionurl": "https://www.gps-speedsurfing.com/?mnu=user&val=415402&uid=24163"
  },
  {
    "rowid": "7",
    "event_id": 769,
    "eventname": "2023 Surf-Forum-One-Hour Challenge 2023",
    "speed": 41.779268,
    "type": "speed_hour",
    "username": "Christian Bratsch",
    "ageclass": "Grand Master (51-60)",
    "weightclass": "71-80",
    "sexe": "Men",
    "spotname": "Gruissan",
    "sessionboard": "PATRIK Slalom 92 III GBM",
    "sessionsail": "Point-7 AC-Z  5.8",
    "sessionfin": "Blipfins BF11 T3s  31",
    "sessionurl": "https://www.gps-speedsurfing.com/?mnu=user&val=407707&uid=26646"
  },
  {
    "rowid": "8",
    "event_id": 769,
    "eventname": "2023 Surf-Forum-One-Hour Challenge 2023",
    "speed": 40.234700000000004,
    "type": "speed_hour",
    "username": "Werner Roeers",
    "ageclass": "Grand Master (51-60)",
    "weightclass": "81-90",
    "sexe": "Men",
    "spotname": " Fehmarn, Orth",
    "sessionboard": "JP Supersport 111 PRO",
    "sessionsail": "Neilpryde V8  6.7",
    "sessionfin": "Tribal Fin weedspeed  31",
    "sessionurl": "https://www.gps-speedsurfing.com/?mnu=user&val=411504&uid=1144"
  },
  {
    "rowid": "9",
    "event_id": 769,
    "eventname": "2023 Surf-Forum-One-Hour Challenge 2023",
    "speed": 40.07728,
    "type": "speed_hour",
    "username": "Jan Heynen",
    "ageclass": "Super Master (61-70)",
    "weightclass": "71-80",
    "sexe": "Men",
    "spotname": "Grevelingenmeer - Zonnemaire",
    "sessionboard": "F2 Sputnik 275",
    "sessionsail": "Loftsails Racing Blade  7.0",
    "sessionfin": "Select Ride  36",
    "sessionurl": "https://www.gps-speedsurfing.com/?mnu=user&val=415583&uid=23556"
  },
  {
    "rowid": "10",
    "event_id": 769,
    "eventname": "2023 Surf-Forum-One-Hour Challenge 2023",
    "speed": 39.764292000000005,
    "type": "speed_hour",
    "username": "Alexander Burger",
    "ageclass": "Grand Master (51-60)",
    "weightclass": "91-100",
    "sexe": "Men",
    "spotname": "Neusiedler See",
    "sessionboard": "Tabou ROCKET PLUS 123 TEAM ",
    "sessionsail": "Point-7 AC-Z  7.8",
    "sessionfin": "Bugfins Slem  39",
    "sessionurl": "https://www.gps-speedsurfing.com/?mnu=user&val=408217&uid=26575"
  },
  {
    "rowid": "11",
    "event_id": 769,
    "eventname": "2023 Surf-Forum-One-Hour Challenge 2023",
    "speed": 38.284544000000004,
    "type": "speed_hour",
    "username": "Jan Behrendt",
    "ageclass": "Senior (19-35)",
    "weightclass": "81-90",
    "sexe": "Men",
    "spotname": "Skaven Strand, Ringkobing Fjord",
    "sessionboard": "PATRIK 140 Air inside V2",
    "sessionsail": "North Sails Warp  8.4",
    "sessionfin": "Sonntag Fins SL  Pro  44",
    "sessionurl": "https://www.gps-speedsurfing.com/?mnu=user&val=410427&uid=5174"
  },
  {
    "rowid": "12",
    "event_id": 769,
    "eventname": "2023 Surf-Forum-One-Hour Challenge 2023",
    "speed": 38.084528,
    "type": "speed_hour",
    "username": "Jan Wim Becker",
    "ageclass": "Junior plus (15-18)",
    "weightclass": "71-80",
    "sexe": "Men",
    "spotname": "Grevelingenmeer - Zonnemaire",
    "sessionboard": "i-99 WCSL 99",
    "sessionsail": "Point-7 AC1  5.6",
    "sessionfin": "Hurricane SR 7 M-  32",
    "sessionurl": "https://www.gps-speedsurfing.com/?mnu=user&val=415316&uid=24496"
  },
  {
    "rowid": "13",
    "event_id": 769,
    "eventname": "2023 Surf-Forum-One-Hour Challenge 2023",
    "speed": 36.971476,
    "type": "speed_hour",
    "username": "Stephan K\u00f6ster",
    "ageclass": "Master (36-50)",
    "weightclass": "71-80",
    "sexe": "Men",
    "spotname": "Veerse Meer",
    "sessionboard": "Phantom IRIS X 83",
    "sessionsail": "Point-7 Foil SL  5.8",
    "sessionfin": "Phantom IRIS X   550",
    "sessionurl": "https://www.gps-speedsurfing.com/?mnu=user&val=409562&uid=25172"
  },
  {
    "rowid": "14",
    "event_id": 769,
    "eventname": "2023 Surf-Forum-One-Hour Challenge 2023",
    "speed": 36.875172000000006,
    "type": "speed_hour",
    "username": "Robert Pietsch",
    "ageclass": "Master (36-50)",
    "weightclass": "91-100",
    "sexe": "Men",
    "spotname": "Walchensee",
    "sessionboard": "Fanatic FALCON 142",
    "sessionsail": "Gun Sails Vector  9.6",
    "sessionfin": "Winheller LWS 8  48",
    "sessionurl": "https://www.gps-speedsurfing.com/?mnu=user&val=409544&uid=26573"
  },
  {
    "rowid": "15",
    "event_id": 769,
    "eventname": "2023 Surf-Forum-One-Hour Challenge 2023",
    "speed": 36.22512,
    "type": "speed_hour",
    "username": "Thomas Kurz",
    "ageclass": "Grand Master (51-60)",
    "weightclass": "81-90",
    "sexe": "Men",
    "spotname": "Chiemsee",
    "sessionboard": "JP Hydrofoil Board",
    "sessionsail": "Neilpryde RS Flight EVO III  7.8",
    "sessionfin": "Neilpryde Flight SLR 70  95",
    "sessionurl": "https://www.gps-speedsurfing.com/?mnu=user&val=418101&uid=1743"
  },
  {
    "rowid": "16",
    "event_id": 769,
    "eventname": "2023 Surf-Forum-One-Hour Challenge 2023",
    "speed": 36.023252,
    "type": "speed_hour",
    "username": "Hannes H\u00e4u\u00dfler",
    "ageclass": "Senior (19-35)",
    "weightclass": "71-80",
    "sexe": "Men",
    "spotname": "Fehmarn, Wulfener Hals",
    "sessionboard": "JP Super Sport",
    "sessionsail": "Loftsails Oxygen  7.3",
    "sessionfin": "Hurricane SR7  46",
    "sessionurl": "https://www.gps-speedsurfing.com/?mnu=user&val=410272&uid=22899"
  },
  {
    "rowid": "17",
    "event_id": 769,
    "eventname": "2023 Surf-Forum-One-Hour Challenge 2023",
    "speed": 36.001028000000005,
    "type": "speed_hour",
    "username": "Michael Still",
    "ageclass": "Grand Master (51-60)",
    "weightclass": "81-90",
    "sexe": "Men",
    "spotname": "Malcesine, Lake Garda",
    "sessionboard": "FMX Invictus 118",
    "sessionsail": "Point-7 AC1  7.8",
    "sessionfin": "MS-Fins X6 S+ 38-2  36",
    "sessionurl": "https://www.gps-speedsurfing.com/?mnu=user&val=404842&uid=26798"
  },
  {
    "rowid": "18",
    "event_id": 769,
    "eventname": "2023 Surf-Forum-One-Hour Challenge 2023",
    "speed": 35.812124000000004,
    "type": "speed_hour",
    "username": "Groneberg Thomas",
    "ageclass": "Master (36-50)",
    "weightclass": "81-90",
    "sexe": "Men",
    "spotname": "Vieste (FG)",
    "sessionboard": "Flikka Hybrid Foil/80/Fin20",
    "sessionsail": "Neilpryde EVO 12  8.2",
    "sessionfin": "not defined -  0",
    "sessionurl": "https://www.gps-speedsurfing.com/?mnu=user&val=410284&uid=26561"
  },
  {
    "rowid": "19",
    "event_id": 769,
    "eventname": "2023 Surf-Forum-One-Hour Challenge 2023",
    "speed": 35.695448000000006,
    "type": "speed_hour",
    "username": "Hans-Dieter Wilshusen",
    "ageclass": "Super Master (61-70)",
    "weightclass": "71-80",
    "sexe": "Men",
    "spotname": "Dorum, Bremerhaven",
    "sessionboard": "RRD FreestyleWave LTD V2",
    "sessionsail": "Loftsails PureLip  5.4",
    "sessionfin": "Tabou Wave  22",
    "sessionurl": "https://www.gps-speedsurfing.com/?mnu=user&val=412593&uid=3855"
  },
  {
    "rowid": "20",
    "event_id": 769,
    "eventname": "2023 Surf-Forum-One-Hour Challenge 2023",
    "speed": 35.539880000000004,
    "type": "speed_hour",
    "username": "Hannes Rieger",
    "ageclass": "Super Master (61-70)",
    "weightclass": "61-70",
    "sexe": "Men",
    "spotname": "Langebaan",
    "sessionboard": "Custom FR 57/21",
    "sessionsail": "Maui Sails Scream  5.5",
    "sessionfin": "Custom SL 81  29",
    "sessionurl": "https://www.gps-speedsurfing.com/?mnu=user&val=401339&uid=24349"
  },
  {
    "rowid": "21",
    "event_id": 769,
    "eventname": "2023 Surf-Forum-One-Hour Challenge 2023",
    "speed": 35.045396,
    "type": "speed_hour",
    "username": "Bernd Winkelmann",
    "ageclass": "Grand Master (51-60)",
    "weightclass": "81-90",
    "sexe": "Men",
    "spotname": "Hvide Sande",
    "sessionboard": "Flikka Freeride Performance 135",
    "sessionsail": "Loft Sails Switchblade   9.5",
    "sessionfin": "not defined Eigenbau  44",
    "sessionurl": "https://www.gps-speedsurfing.com/?mnu=user&val=412031&uid=26555"
  },
  {
    "rowid": "22",
    "event_id": 769,
    "eventname": "2023 Surf-Forum-One-Hour Challenge 2023",
    "speed": 34.45831200000001,
    "type": "speed_hour",
    "username": "Bernhard Brozy",
    "ageclass": "Super Master (61-70)",
    "weightclass": "71-80",
    "sexe": "Men",
    "spotname": "Wolderwijd - Strand Horst",
    "sessionboard": "Starboard  iSonic 73 Carbon Reflex ",
    "sessionsail": "Severne Overdrive M4  7.8",
    "sessionfin": "C-Fins 6.0  37",
    "sessionurl": "https://www.gps-speedsurfing.com/?mnu=user&val=412508&uid=3818"
  },
  {
    "rowid": "23",
    "event_id": 769,
    "eventname": "2023 Surf-Forum-One-Hour Challenge 2023",
    "speed": 34.276816,
    "type": "speed_hour",
    "username": "Niels L\u00fcttge",
    "ageclass": "Grand Master (51-60)",
    "weightclass": "81-90",
    "sexe": "Men",
    "spotname": "Steinhuder-Meer",
    "sessionboard": "Tabou Rocket Plus 123 Carbon Flex",
    "sessionsail": "Duotone warp 2022 FIN  7.8",
    "sessionfin": "Sonntag Fins SL-pro 2  40",
    "sessionurl": "https://www.gps-speedsurfing.com/?mnu=user&val=412464&uid=25477"
  },
  {
    "rowid": "24",
    "event_id": 769,
    "eventname": "2023 Surf-Forum-One-Hour Challenge 2023",
    "speed": 33.860116000000005,
    "type": "speed_hour",
    "username": "Tatiana Dianova",
    "ageclass": "Master (36-50)",
    "weightclass": "51-60",
    "sexe": "Woman",
    "spotname": " Fehmarn, Orth",
    "sessionboard": "PATRIK Slalom 95 AI",
    "sessionsail": "Avanti Sails Machine M5  7.0",
    "sessionfin": "Maui Ultra Fins Slalom Carbon Weed  28",
    "sessionurl": "https://www.gps-speedsurfing.com/?mnu=user&val=416562&uid=25062"
  },
  {
    "rowid": "25",
    "event_id": 769,
    "eventname": "2023 Surf-Forum-One-Hour Challenge 2023",
    "speed": 33.819372,
    "type": "speed_hour",
    "username": "Thomas Oberhofer",
    "ageclass": "Grand Master (51-60)",
    "weightclass": "81-90",
    "sexe": "Men",
    "spotname": "Hvide Sande",
    "sessionboard": "Starboard  iSonic 73 Carbon Reflex ",
    "sessionsail": "Gun Sails GSR  7.1",
    "sessionfin": "C-Fins 4.4  37",
    "sessionurl": "https://www.gps-speedsurfing.com/?mnu=user&val=406910&uid=26495"
  },
  {
    "rowid": "26",
    "event_id": 769,
    "eventname": "2023 Surf-Forum-One-Hour Challenge 2023",
    "speed": 33.800852000000006,
    "type": "speed_hour",
    "username": "Rainer Haemmerle",
    "ageclass": "Master (36-50)",
    "weightclass": "81-90",
    "sexe": "Men",
    "spotname": "Palo Alto Yacht Harbor - SFB, CA",
    "sessionboard": "Starboard iSonic 72 Carbon Reflex ",
    "sessionsail": "Severne Overdrive M2  7.8",
    "sessionfin": "Z-fins Z-SLM  37",
    "sessionurl": "https://www.gps-speedsurfing.com/?mnu=user&val=415610&uid=26366"
  },
  {
    "rowid": "27",
    "event_id": 769,
    "eventname": "2023 Surf-Forum-One-Hour Challenge 2023",
    "speed": 33.208212,
    "type": "speed_hour",
    "username": "Steven Strausi",
    "ageclass": "Senior (19-35)",
    "weightclass": "71-80",
    "sexe": "Men",
    "spotname": "Berlingen",
    "sessionboard": "PATRIK qt-wave",
    "sessionsail": "Gun Sails Seal  4.2",
    "sessionfin": "K4 3SW  22",
    "sessionurl": "https://www.gps-speedsurfing.com/?mnu=user&val=418198&uid=26846"
  },
  {
    "rowid": "28",
    "event_id": 769,
    "eventname": "2023 Surf-Forum-One-Hour Challenge 2023",
    "speed": 33.152652,
    "type": "speed_hour",
    "username": "Radeleff Boris",
    "ageclass": "Grand Master (51-60)",
    "weightclass": "71-80",
    "sexe": "Men",
    "spotname": "F\u00f6rmitzspeicher",
    "sessionboard": "FMX Hyperion 178 LR",
    "sessionsail": "Patrik Foil+  8.0",
    "sessionfin": "Sabfoil 1000  107",
    "sessionurl": "https://www.gps-speedsurfing.com/?mnu=user&val=418735&uid=26553"
  },
  {
    "rowid": "29",
    "event_id": 769,
    "eventname": "2023 Surf-Forum-One-Hour Challenge 2023",
    "speed": 31.337692,
    "type": "speed_hour",
    "username": "Christian Wrobel",
    "ageclass": "Master (36-50)",
    "weightclass": "71-80",
    "sexe": "Men",
    "spotname": "Urnersee - Sisikon",
    "sessionboard": "PATRIK Slalom 128v2",
    "sessionsail": "Gun Sails GSR  7.7",
    "sessionfin": "Winheller LWS 8  45",
    "sessionurl": "https://www.gps-speedsurfing.com/?mnu=user&val=412255&uid=19345"
  },
  {
    "rowid": "30",
    "event_id": 769,
    "eventname": "2023 Surf-Forum-One-Hour Challenge 2023",
    "speed": 31.078412,
    "type": "speed_hour",
    "username": "Volker Dunker",
    "ageclass": "Super Master (61-70)",
    "weightclass": "71-80",
    "sexe": "Men",
    "spotname": "Skaven Strand, Ringkobing Fjord",
    "sessionboard": "Tabou Rocket Wide 118 LTD",
    "sessionsail": "Gun Sails Rapid  6.2",
    "sessionfin": "ART Slalom Blade 41  41",
    "sessionurl": "https://www.gps-speedsurfing.com/?mnu=user&val=410420&uid=5860"
  },
  {
    "rowid": "31",
    "event_id": 769,
    "eventname": "2023 Surf-Forum-One-Hour Challenge 2023",
    "speed": 30.524664,
    "type": "speed_hour",
    "username": "Josef Gredler",
    "ageclass": "Super Master (61-70)",
    "weightclass": "71-80",
    "sexe": "Men",
    "spotname": "Hotel-Pier Lake-Garda",
    "sessionboard": "- Horney Slalom",
    "sessionsail": "S2 Maui Wicked  7.0",
    "sessionfin": "- JoseFIN  36",
    "sessionurl": "https://www.gps-speedsurfing.com/?mnu=user&val=415967&uid=26294"
  },
  {
    "rowid": "32",
    "event_id": 769,
    "eventname": "2023 Surf-Forum-One-Hour Challenge 2023",
    "speed": 30.432064,
    "type": "speed_hour",
    "username": "S\u00f6nke Schmidt",
    "ageclass": "Master (36-50)",
    "weightclass": "71-80",
    "sexe": "Men",
    "spotname": "Torbole, Lake Garda",
    "sessionboard": "Tabou Fifty Team",
    "sessionsail": "Duotone E Type  6.6",
    "sessionfin": "not defined -  0",
    "sessionurl": "https://www.gps-speedsurfing.com/?mnu=user&val=404759&uid=26559"
  },
  {
    "rowid": "33",
    "event_id": 769,
    "eventname": "2023 Surf-Forum-One-Hour Challenge 2023",
    "speed": 29.444948,
    "type": "speed_hour",
    "username": "Wulf Schirbel",
    "ageclass": "Master (36-50)",
    "weightclass": "81-90",
    "sexe": "Men",
    "spotname": "D\u00fcmmer See",
    "sessionboard": "JP X-cite Ride 120",
    "sessionsail": "Neilpryde Fusion  6.1",
    "sessionfin": "JP Freeride  38",
    "sessionurl": "https://www.gps-speedsurfing.com/?mnu=user&val=415286&uid=26564"
  },
  {
    "rowid": "34",
    "event_id": 769,
    "eventname": "2023 Surf-Forum-One-Hour Challenge 2023",
    "speed": 28.281892000000003,
    "type": "speed_hour",
    "username": "R\u00fcdiger Rumpel",
    "ageclass": "Grand Master (51-60)",
    "weightclass": "81-90",
    "sexe": "Men",
    "spotname": "Wei\u00dfensee (F\u00fcssen)",
    "sessionboard": "Flikka Slalom 130",
    "sessionsail": "Duotone Warp Fin  7.7",
    "sessionfin": "MS-Fins X7  420",
    "sessionurl": "https://www.gps-speedsurfing.com/?mnu=user&val=416077&uid=24437"
  },
  {
    "rowid": "35",
    "event_id": 769,
    "eventname": "2023 Surf-Forum-One-Hour Challenge 2023",
    "speed": 26.483600000000003,
    "type": "speed_hour",
    "username": "Tim Otte",
    "ageclass": "Grand Master (51-60)",
    "weightclass": "101-110",
    "sexe": "Men",
    "spotname": "Karpathos",
    "sessionboard": "Starboard Isonic 72 Carbon",
    "sessionsail": "Severne Mach 6  7.5",
    "sessionfin": "Maui Ultra Fins Slalom Pro Carbon  36",
    "sessionurl": "https://www.gps-speedsurfing.com/?mnu=user&val=419303&uid=2554"
  },
  {
    "rowid": "36",
    "event_id": 769,
    "eventname": "2023 Surf-Forum-One-Hour Challenge 2023",
    "speed": 22.138808,
    "type": "speed_hour",
    "username": "Kai Hartnack",
    "ageclass": "Master (36-50)",
    "weightclass": "91-100",
    "sexe": "Men",
    "spotname": "Oostvoornse Meer",
    "sessionboard": "JP Super Lightwind pro",
    "sessionsail": "Gun Sails Rapid  6.7",
    "sessionfin": "not defined -  0",
    "sessionurl": "https://www.gps-speedsurfing.com/?mnu=user&val=419016&uid=26995"
  },
  {
    "rowid": "37",
    "event_id": 769,
    "eventname": "2023 Surf-Forum-One-Hour Challenge 2023",
    "speed": 20.94612,
    "type": "speed_hour",
    "username": "Thorsten H\u00e4ndel",
    "ageclass": "Grand Master (51-60)",
    "weightclass": "101-110",
    "sexe": "Men",
    "spotname": "Steinhuder-Meer",
    "sessionboard": "Tabou Manta 71",
    "sessionsail": "Severne Mach 1  7.0",
    "sessionfin": "Feine Finnen BASTARD SLALOM   36",
    "sessionurl": "https://www.gps-speedsurfing.com/?mnu=user&val=415721&uid=5509"
  },
  {
    "rowid": "38",
    "event_id": 769,
    "eventname": "2023 Surf-Forum-One-Hour Challenge 2023",
    "speed": 20.03864,
    "type": "speed_hour",
    "username": "Sebastian Thoem",
    "ageclass": "Master (36-50)",
    "weightclass": "81-90",
    "sexe": "Men",
    "spotname": "Lac Bay",
    "sessionboard": "Future Fly Dark Horse 107",
    "sessionsail": "Severne Overdrive M3  7.8",
    "sessionfin": "Z-fins SLM S-  37",
    "sessionurl": "https://www.gps-speedsurfing.com/?mnu=user&val=404939&uid=26404"
  },
  {
    "rowid": "39",
    "event_id": 769,
    "eventname": "2023 Surf-Forum-One-Hour Challenge 2023",
    "speed": 19.894184000000003,
    "type": "speed_hour",
    "username": "Christoph Hinze",
    "ageclass": "Grand Master (51-60)",
    "weightclass": "71-80",
    "sexe": "Men",
    "spotname": "Fehmarn, Wulfener Hals",
    "sessionboard": "Tabou Rocket Plus 133 LTD",
    "sessionsail": "North Sails E-Type  6.6",
    "sessionfin": "Maui Ultra Fins Slalom-Weed   32",
    "sessionurl": "https://www.gps-speedsurfing.com/?mnu=user&val=411597&uid=26552"
  },
  {
    "rowid": "40",
    "event_id": 769,
    "eventname": "2023 Surf-Forum-One-Hour Challenge 2023",
    "speed": 14.321516,
    "type": "speed_hour",
    "username": "Alexander Nitsche",
    "ageclass": "Master (36-50)",
    "weightclass": "91-100",
    "sexe": "Men",
    "spotname": "Fehmarn, Wulfener Hals",
    "sessionboard": "PATRIK Slalom 125",
    "sessionsail": "GA-sails Vapor  7.9",
    "sessionfin": "Maui Ultra Fins Slalom-Weed   32",
    "sessionurl": "https://www.gps-speedsurfing.com/?mnu=user&val=411606&uid=25960"
  },
  {
    "rowid": "41",
    "event_id": 769,
    "eventname": "2023 Surf-Forum-One-Hour Challenge 2023",
    "speed": 13.839996000000001,
    "type": "speed_hour",
    "username": "Nicole Skodda",
    "ageclass": "Master (36-50)",
    "weightclass": "51-60",
    "sexe": "Woman",
    "spotname": "Draget, Limfjorden",
    "sessionboard": "i-99 Stylewave 104l  cvk",
    "sessionsail": "Loftsails Wavescape  5.6",
    "sessionfin": "Teknosport Weed Wave  23",
    "sessionurl": "https://www.gps-speedsurfing.com/?mnu=user&val=413797&uid=6348"
  }
]