[
  {
    "rowid": "1",
    "event_id": 816,
    "eventname": "2023 Spanish Challenge",
    "speed": 74.41150800000001,
    "type": "speed_500",
    "username": " Antonio Mora",
    "ageclass": "Master (36-50)",
    "weightclass": "71-80",
    "sexe": "Men",
    "spotname": "Tarifa, Campo de football",
    "sessionboard": "JP Luderitz 37 Custom Speed",
    "sessionsail": "Gun Sails GSR  5.0",
    "sessionfin": "Tribal Fin Asy Speed   18",
    "sessionurl": "https://www.gps-speedsurfing.com/?mnu=user&val=418313&uid=26004"
  },
  {
    "rowid": "2",
    "event_id": 816,
    "eventname": "2023 Spanish Challenge",
    "speed": 71.161248,
    "type": "speed_500",
    "username": "Jose Luis Morales Romacho",
    "ageclass": "Master (36-50)",
    "weightclass": "71-80",
    "sexe": "Men",
    "spotname": "Tarifa, Campo de football",
    "sessionboard": "Starboard iSonic Speed Special W54",
    "sessionsail": "Neilpryde EVO X  5.2",
    "sessionfin": "Select Caspar Speed GPS  23",
    "sessionurl": "https://www.gps-speedsurfing.com/?mnu=user&val=418309&uid=22828"
  },
  {
    "rowid": "3",
    "event_id": 816,
    "eventname": "2023 Spanish Challenge",
    "speed": 68.909216,
    "type": "speed_500",
    "username": "Kai Kaufmann",
    "ageclass": "Master (36-50)",
    "weightclass": "91-100",
    "sexe": "Men",
    "spotname": "Fuerteventura, Sotavento",
    "sessionboard": "Starboard iSonic Speed Special W54",
    "sessionsail": "RRD X-Wing Y25  5.6",
    "sessionfin": "Hurricane SS M-  28",
    "sessionurl": "https://www.gps-speedsurfing.com/?mnu=user&val=412658&uid=16746"
  },
  {
    "rowid": "4",
    "event_id": 816,
    "eventname": "2023 Spanish Challenge",
    "speed": 68.281388,
    "type": "speed_500",
    "username": "Enrique del Valle",
    "ageclass": "Grand Master (51-60)",
    "weightclass": "81-90",
    "sexe": "Men",
    "spotname": "Tarifa, Campo de football",
    "sessionboard": "Tribal board Rapid Speed 53",
    "sessionsail": "KA Sails KA Speed Proto  5.4",
    "sessionfin": "Tribal Fin ASY Speed Carbon   23",
    "sessionurl": "https://www.gps-speedsurfing.com/?mnu=user&val=406981&uid=23714"
  },
  {
    "rowid": "5",
    "event_id": 816,
    "eventname": "2023 Spanish Challenge",
    "speed": 67.138704,
    "type": "speed_500",
    "username": "Oliver Schaarschmidt",
    "ageclass": "Grand Master (51-60)",
    "weightclass": "71-80",
    "sexe": "Men",
    "spotname": "Fuerteventura, Sotavento",
    "sessionboard": "PATRIK Slalom 85",
    "sessionsail": "Patrik Race SF  6.2",
    "sessionfin": "Z-fins SF S  29",
    "sessionurl": "https://www.gps-speedsurfing.com/?mnu=user&val=414788&uid=2357"
  },
  {
    "rowid": "6",
    "event_id": 816,
    "eventname": "2023 Spanish Challenge",
    "speed": 63.562492,
    "type": "speed_500",
    "username": "Manuel Pousa ",
    "ageclass": "Master (36-50)",
    "weightclass": "71-80",
    "sexe": "Men",
    "spotname": "Tarifa, Campo de football",
    "sessionboard": "Custom SBT",
    "sessionsail": "Gun Sails GSR  5.0",
    "sessionfin": "Sonntag Fins 21  21",
    "sessionurl": "https://www.gps-speedsurfing.com/?mnu=user&val=410996&uid=26477"
  },
  {
    "rowid": "7",
    "event_id": 816,
    "eventname": "2023 Spanish Challenge",
    "speed": 63.312472,
    "type": "speed_500",
    "username": "Antonio Calvo Calvo",
    "ageclass": "Senior (19-35)",
    "weightclass": "61-70",
    "sexe": "Men",
    "spotname": "Tarifa, Campo de football",
    "sessionboard": "Custom SBT",
    "sessionsail": "KA Sails Koncept  4.2",
    "sessionfin": "Z-fins Speed Asy S   20",
    "sessionurl": "https://www.gps-speedsurfing.com/?mnu=user&val=418202&uid=26053"
  },
  {
    "rowid": "8",
    "event_id": 816,
    "eventname": "2023 Spanish Challenge",
    "speed": 58.33985200000001,
    "type": "speed_500",
    "username": "Ra\u00fal Mart\u00ednez Alvarez",
    "ageclass": "Master (36-50)",
    "weightclass": "111-150",
    "sexe": "Men",
    "spotname": "Mar Menor, Lopagan El Molino",
    "sessionboard": "Mistral Mistral 112",
    "sessionsail": "KA Sails Race  7.7",
    "sessionfin": "Tribal Fin Weedspeed  35",
    "sessionurl": "https://www.gps-speedsurfing.com/?mnu=user&val=408924&uid=23628"
  },
  {
    "rowid": "9",
    "event_id": 816,
    "eventname": "2023 Spanish Challenge",
    "speed": 58.263920000000006,
    "type": "speed_500",
    "username": "Dani Coca Serra",
    "ageclass": "Master (36-50)",
    "weightclass": "71-80",
    "sexe": "Men",
    "spotname": "Fornells",
    "sessionboard": "JP Speed 45 Pro Edition",
    "sessionsail": "Loftsails Speed Blade  5.6",
    "sessionfin": "Tribal Fin asy (S) speed carbon  22",
    "sessionurl": "https://www.gps-speedsurfing.com/?mnu=user&val=401252&uid=19419"
  },
  {
    "rowid": "10",
    "event_id": 816,
    "eventname": "2023 Spanish Challenge",
    "speed": 55.626672000000006,
    "type": "speed_500",
    "username": "Jose Luis Boronat Suay",
    "ageclass": "Senior (19-35)",
    "weightclass": "71-80",
    "sexe": "Men",
    "spotname": "Valencia",
    "sessionboard": "Starboard iSonic 73 Carbon Reflex",
    "sessionsail": "Severne Mach 4  7.8",
    "sessionfin": "Sonntag Fins SL-PRO  37",
    "sessionurl": "https://www.gps-speedsurfing.com/?mnu=user&val=403400&uid=24605"
  },
  {
    "rowid": "11",
    "event_id": 816,
    "eventname": "2023 Spanish Challenge",
    "speed": 55.248864000000005,
    "type": "speed_500",
    "username": "Rafael Cuesta",
    "ageclass": "Super Master (61-70)",
    "weightclass": "71-80",
    "sexe": "Men",
    "spotname": "Embalse de Pedrezuela",
    "sessionboard": "RRD X-Fire 114 V11 LTD",
    "sessionsail": "Duotone Warp 2019  7.7",
    "sessionfin": "- Aleta Gregor Custom SL3 pro  36",
    "sessionurl": "https://www.gps-speedsurfing.com/?mnu=user&val=406173&uid=22584"
  },
  {
    "rowid": "12",
    "event_id": 816,
    "eventname": "2023 Spanish Challenge",
    "speed": 54.667336000000006,
    "type": "speed_500",
    "username": "Salvador Ya\u00f1ez",
    "ageclass": "Grand Master (51-60)",
    "weightclass": "81-90",
    "sexe": "Men",
    "spotname": "Tarifa, Campo de football",
    "sessionboard": "Starboard Isonic Speed W49",
    "sessionsail": "Severne Mach 3  7.0",
    "sessionfin": "Gasoil Fins ELS-T H PRO 320  21",
    "sessionurl": "https://www.gps-speedsurfing.com/?mnu=user&val=415823&uid=13637"
  },
  {
    "rowid": "13",
    "event_id": 816,
    "eventname": "2023 Spanish Challenge",
    "speed": 53.858012,
    "type": "speed_500",
    "username": "Alberto Marugan",
    "ageclass": "Grand Master (51-60)",
    "weightclass": "81-90",
    "sexe": "Men",
    "spotname": "Aloc\u00e9n, Entrepe\u00f1as",
    "sessionboard": "Fanatic Falcon TE 115",
    "sessionsail": "Duotone Warp-Fin 2021  7.7",
    "sessionfin": "Z-fins SF S-  37",
    "sessionurl": "https://www.gps-speedsurfing.com/?mnu=user&val=405563&uid=25183"
  },
  {
    "rowid": "14",
    "event_id": 816,
    "eventname": "2023 Spanish Challenge",
    "speed": 49.848432,
    "type": "speed_500",
    "username": "Albert Ros Vicens",
    "ageclass": "Master (36-50)",
    "weightclass": "91-100",
    "sexe": "Men",
    "spotname": "Es Barcarets",
    "sessionboard": "Starboard iSonic 85 Slalom Carbon",
    "sessionsail": "Severne Reflex R8  8.6",
    "sessionfin": "Z-fins SL 46 S-  46",
    "sessionurl": "https://www.gps-speedsurfing.com/?mnu=user&val=415777&uid=23412"
  },
  {
    "rowid": "15",
    "event_id": 816,
    "eventname": "2023 Spanish Challenge",
    "speed": 49.176156000000006,
    "type": "speed_500",
    "username": "Raimundo Sala Albert",
    "ageclass": "Ultimate Master (71-99)",
    "weightclass": "81-90",
    "sexe": "Men",
    "spotname": "La Loteta",
    "sessionboard": "AV Modena Slalom 62",
    "sessionsail": "Point-7 AC1  5.6",
    "sessionfin": "Tribal Fin Slalom mk2  32",
    "sessionurl": "https://www.gps-speedsurfing.com/?mnu=user&val=404684&uid=22440"
  },
  {
    "rowid": "16",
    "event_id": 816,
    "eventname": "2023 Spanish Challenge",
    "speed": 47.044504,
    "type": "speed_500",
    "username": "Luis Vierna",
    "ageclass": "Master (36-50)",
    "weightclass": "81-90",
    "sexe": "Men",
    "spotname": "Embalse de Pedrezuela",
    "sessionboard": "i-99 NoveNove WCSL 139",
    "sessionsail": "Neilpryde Evo X1  8.6",
    "sessionfin": "- Chopper fins  44",
    "sessionurl": "https://www.gps-speedsurfing.com/?mnu=user&val=403186&uid=22002"
  },
  {
    "rowid": "17",
    "event_id": 816,
    "eventname": "2023 Spanish Challenge",
    "speed": 47.03154,
    "type": "speed_500",
    "username": "Boris Mueller",
    "ageclass": "Master (36-50)",
    "weightclass": "71-80",
    "sexe": "Men",
    "spotname": "Fuerteventura Sotavento",
    "sessionboard": "F2 Wave",
    "sessionsail": "Gaastra Heat wave  4.7",
    "sessionfin": "North Shore Wave  23",
    "sessionurl": "https://www.gps-speedsurfing.com/?mnu=user&val=419258&uid=24640"
  },
  {
    "rowid": "18",
    "event_id": 816,
    "eventname": "2023 Spanish Challenge",
    "speed": 46.853748,
    "type": "speed_500",
    "username": "Carlos Reyes",
    "ageclass": "Master (36-50)",
    "weightclass": "61-70",
    "sexe": "Men",
    "spotname": "Valmayor Lake, Madrid",
    "sessionboard": "Starboard Isonic 67 Carbon reflex ",
    "sessionsail": "Loftsails Racing Blade  7.0",
    "sessionfin": "not defined -  0",
    "sessionurl": "https://www.gps-speedsurfing.com/?mnu=user&val=405770&uid=26775"
  },
  {
    "rowid": "19",
    "event_id": 816,
    "eventname": "2023 Spanish Challenge",
    "speed": 44.842476000000005,
    "type": "speed_500",
    "username": "Jose Manuel Torres Garcia",
    "ageclass": "Ultimate Master (71-99)",
    "weightclass": "101-110",
    "sexe": "Men",
    "spotname": "Santa Pola",
    "sessionboard": "i-99 WCSL",
    "sessionsail": "Loft Sails Racinblade  9.0",
    "sessionfin": "Z-fins SLM S-  46",
    "sessionurl": "https://www.gps-speedsurfing.com/?mnu=user&val=405603&uid=25290"
  },
  {
    "rowid": "20",
    "event_id": 816,
    "eventname": "2023 Spanish Challenge",
    "speed": 35.30838000000001,
    "type": "speed_500",
    "username": "Gaspar Evelio Cascon Schwarzenlander",
    "ageclass": "Youth (0-10)",
    "weightclass": "0-40",
    "sexe": "Men",
    "spotname": "Gran Canaria, Bah\u00eda de Formas (Salinas de Arinaga)",
    "sessionboard": "Goya Bolt",
    "sessionsail": "Simmer Sails Icon  4.2",
    "sessionfin": "MFC H1  30",
    "sessionurl": "https://www.gps-speedsurfing.com/?mnu=user&val=406923&uid=26847"
  },
  {
    "rowid": "21",
    "event_id": 816,
    "eventname": "2023 Spanish Challenge",
    "speed": 29.728304,
    "type": "speed_500",
    "username": "Lea Sophie Hagedorn",
    "ageclass": "Junior plus (15-18)",
    "weightclass": "51-60",
    "sexe": "Woman",
    "spotname": "Gran Canaria, Bah\u00eda de Formas (Salinas de Arinaga)",
    "sessionboard": "PATRIK Slalom 87 V2",
    "sessionsail": "KA Sails Koncept 2013  4.6",
    "sessionfin": "Choco Fins Fireblade 2  30",
    "sessionurl": "https://www.gps-speedsurfing.com/?mnu=user&val=414041&uid=25422"
  }
]