[
  {
    "rowid": "1",
    "event_id": 810,
    "eventname": "2023 Odyssey of Speed",
    "speed": 49.153932000000005,
    "type": "speed_halfhour",
    "username": "Twan Verseput ",
    "ageclass": "Senior (19-35)",
    "weightclass": "91-100",
    "sexe": "Men",
    "spotname": "Karpathos",
    "sessionboard": "PATRIK Slalom Air Inside",
    "sessionsail": "Patrik Race+  7.0",
    "sessionfin": "Sonntag Fins SL-Pro  36",
    "sessionurl": "https://www.gps-speedsurfing.com/?mnu=user&val=415739&uid=3923"
  },
  {
    "rowid": "2",
    "event_id": 810,
    "eventname": "2023 Odyssey of Speed",
    "speed": 43.081224000000006,
    "type": "speed_halfhour",
    "username": "Mixalis Damigos",
    "ageclass": "Senior (19-35)",
    "weightclass": "81-90",
    "sexe": "Men",
    "spotname": "Kamari - Avis",
    "sessionboard": "RRD X-Fire LTD V7 114",
    "sessionsail": "GA-sails vapor  7.1",
    "sessionfin": "Z-fins Z-SLM  37",
    "sessionurl": "https://www.gps-speedsurfing.com/?mnu=user&val=418114&uid=26300"
  },
  {
    "rowid": "3",
    "event_id": 810,
    "eventname": "2023 Odyssey of Speed",
    "speed": 42.20708,
    "type": "speed_halfhour",
    "username": "Antony Bourmas",
    "ageclass": "Master (36-50)",
    "weightclass": "71-80",
    "sexe": "Men",
    "spotname": "Achladi Fthiotidas",
    "sessionboard": "RRD X-Fire 108 V10 LTD",
    "sessionsail": "RRD xwing MK1  7.0",
    "sessionfin": "not defined -  0",
    "sessionurl": "https://www.gps-speedsurfing.com/?mnu=user&val=418600&uid=26748"
  },
  {
    "rowid": "4",
    "event_id": 810,
    "eventname": "2023 Odyssey of Speed",
    "speed": 42.064476000000006,
    "type": "speed_halfhour",
    "username": "Alexandros Petikidis",
    "ageclass": "Grand Master (51-60)",
    "weightclass": "81-90",
    "sexe": "Men",
    "spotname": "Karpathos",
    "sessionboard": "Tabou Manta 71",
    "sessionsail": "GA-sails Vapor  6.9",
    "sessionfin": "Z-fins SLM S-  36",
    "sessionurl": "https://www.gps-speedsurfing.com/?mnu=user&val=419514&uid=4152"
  },
  {
    "rowid": "5",
    "event_id": 810,
    "eventname": "2023 Odyssey of Speed",
    "speed": 41.61444,
    "type": "speed_halfhour",
    "username": "Dimitris Lentzos",
    "ageclass": "Master (36-50)",
    "weightclass": "81-90",
    "sexe": "Men",
    "spotname": "VALTOS",
    "sessionboard": "Starboard isonic 85 Reflex Carbon ",
    "sessionsail": "Gun Sails race  8.4",
    "sessionfin": "Z-fins SL S-  44",
    "sessionurl": "https://www.gps-speedsurfing.com/?mnu=user&val=416932&uid=18214"
  },
  {
    "rowid": "6",
    "event_id": 810,
    "eventname": "2023 Odyssey of Speed",
    "speed": 40.864380000000004,
    "type": "speed_halfhour",
    "username": "Morten Knutsen",
    "ageclass": "Grand Master (51-60)",
    "weightclass": "81-90",
    "sexe": "Men",
    "spotname": "Karpathos",
    "sessionboard": "AV Modena Slalom 68",
    "sessionsail": "Point-7 AC1  7.0",
    "sessionfin": "Tribal Fin MKII 35  35",
    "sessionurl": "https://www.gps-speedsurfing.com/?mnu=user&val=418579&uid=23429"
  },
  {
    "rowid": "7",
    "event_id": 810,
    "eventname": "2023 Odyssey of Speed",
    "speed": 40.453236000000004,
    "type": "speed_halfhour",
    "username": "Eric Groot-van Ederen",
    "ageclass": "Master (36-50)",
    "weightclass": "101-110",
    "sexe": "Men",
    "spotname": "Karpathos",
    "sessionboard": "Starboard Isonic 72 Carbon Reflex",
    "sessionsail": "Loftsails Speed Blade  6.3",
    "sessionfin": "Finish Fast Speed B3   38",
    "sessionurl": "https://www.gps-speedsurfing.com/?mnu=user&val=414853&uid=2735"
  },
  {
    "rowid": "8",
    "event_id": 810,
    "eventname": "2023 Odyssey of Speed",
    "speed": 39.279068,
    "type": "speed_halfhour",
    "username": "Thanasis Savvakis",
    "ageclass": "Master (36-50)",
    "weightclass": "71-80",
    "sexe": "Men",
    "spotname": "LIMNI",
    "sessionboard": "RRD X-fire 114",
    "sessionsail": "RRD X-Wing Y25  7.8",
    "sessionfin": "Z-fins sl s-  37",
    "sessionurl": "https://www.gps-speedsurfing.com/?mnu=user&val=417610&uid=26346"
  },
  {
    "rowid": "9",
    "event_id": 810,
    "eventname": "2023 Odyssey of Speed",
    "speed": 39.230916,
    "type": "speed_halfhour",
    "username": "Minos Efstathiadis",
    "ageclass": "Grand Master (51-60)",
    "weightclass": "91-100",
    "sexe": "Men",
    "spotname": "Psathopirgos",
    "sessionboard": "Tabou Manta 81",
    "sessionsail": "GA-sails Vapor  7.7",
    "sessionfin": "Ufo Slalom  44",
    "sessionurl": "https://www.gps-speedsurfing.com/?mnu=user&val=410527&uid=962"
  },
  {
    "rowid": "10",
    "event_id": 810,
    "eventname": "2023 Odyssey of Speed",
    "speed": 38.99386,
    "type": "speed_halfhour",
    "username": "Spiros Chouliaras",
    "ageclass": "Master (36-50)",
    "weightclass": "71-80",
    "sexe": "Men",
    "spotname": "VALTOS",
    "sessionboard": "Tabou Manta 71",
    "sessionsail": "Gaastra Phantom   7.8",
    "sessionfin": "Z-fins Zfin SL S-  37",
    "sessionurl": "https://www.gps-speedsurfing.com/?mnu=user&val=411302&uid=23430"
  },
  {
    "rowid": "11",
    "event_id": 810,
    "eventname": "2023 Odyssey of Speed",
    "speed": 37.408548,
    "type": "speed_halfhour",
    "username": "Giannis Reglis",
    "ageclass": "Master (36-50)",
    "weightclass": "71-80",
    "sexe": "Men",
    "spotname": "VALTOS",
    "sessionboard": "Tabou Manta 66",
    "sessionsail": "Gaastra Vapor  7.8",
    "sessionfin": "Sonntag Fins SL-pro  34",
    "sessionurl": "https://www.gps-speedsurfing.com/?mnu=user&val=419379&uid=22406"
  },
  {
    "rowid": "12",
    "event_id": 810,
    "eventname": "2023 Odyssey of Speed",
    "speed": 35.38986800000001,
    "type": "speed_halfhour",
    "username": "Konstantinos Dimopoulos",
    "ageclass": "Master (36-50)",
    "weightclass": "71-80",
    "sexe": "Men",
    "spotname": "Rodini",
    "sessionboard": "Starboard slalom",
    "sessionsail": "Point-7 AC1  7.1",
    "sessionfin": "Z-fins SL S  34",
    "sessionurl": "https://www.gps-speedsurfing.com/?mnu=user&val=412642&uid=21831"
  },
  {
    "rowid": "13",
    "event_id": 810,
    "eventname": "2023 Odyssey of Speed",
    "speed": 35.182444000000004,
    "type": "speed_halfhour",
    "username": "Ilias Tsekouras",
    "ageclass": "Master (36-50)",
    "weightclass": "81-90",
    "sexe": "Men",
    "spotname": "Raches Bojo ",
    "sessionboard": "Fanatic falcon slalom 110",
    "sessionsail": "Duotone Warp  7.7",
    "sessionfin": "Z-fins Z SF S-  36",
    "sessionurl": "https://www.gps-speedsurfing.com/?mnu=user&val=418962&uid=6030"
  },
  {
    "rowid": "14",
    "event_id": 810,
    "eventname": "2023 Odyssey of Speed",
    "speed": 34.736112000000006,
    "type": "speed_halfhour",
    "username": "Doxis Milidakis",
    "ageclass": "Grand Master (51-60)",
    "weightclass": "71-80",
    "sexe": "Men",
    "spotname": "VALTOS",
    "sessionboard": "Starboard iSonic Carbon 67",
    "sessionsail": "Neilpryde RS Racing EVO XII  7.4",
    "sessionfin": "Custom CARPENTER  34",
    "sessionurl": "https://www.gps-speedsurfing.com/?mnu=user&val=417878&uid=3708"
  },
  {
    "rowid": "15",
    "event_id": 810,
    "eventname": "2023 Odyssey of Speed",
    "speed": 34.508316,
    "type": "speed_halfhour",
    "username": "Manolis Kapnisakis",
    "ageclass": "Master (36-50)",
    "weightclass": "91-100",
    "sexe": "Men",
    "spotname": "Finikounda",
    "sessionboard": "Tabou Manta 71",
    "sessionsail": "GA-sails Vapor  7.9",
    "sessionfin": "Z-fins ZSLM 38--  38",
    "sessionurl": "https://www.gps-speedsurfing.com/?mnu=user&val=414858&uid=1193"
  },
  {
    "rowid": "16",
    "event_id": 810,
    "eventname": "2023 Odyssey of Speed",
    "speed": 33.508236000000004,
    "type": "speed_halfhour",
    "username": "Tim Otte",
    "ageclass": "Grand Master (51-60)",
    "weightclass": "101-110",
    "sexe": "Men",
    "spotname": "Karpathos",
    "sessionboard": "Starboard Isonic 72 Carbon",
    "sessionsail": "Severne Mach 6  7.5",
    "sessionfin": "Maui Ultra Fins Slalom Pro Carbon  36",
    "sessionurl": "https://www.gps-speedsurfing.com/?mnu=user&val=419303&uid=2554"
  },
  {
    "rowid": "17",
    "event_id": 810,
    "eventname": "2023 Odyssey of Speed",
    "speed": 33.017456,
    "type": "speed_halfhour",
    "username": "Till Kramann",
    "ageclass": "Master (36-50)",
    "weightclass": "81-90",
    "sexe": "Men",
    "spotname": "VALTOS",
    "sessionboard": "Tabou Manta 85",
    "sessionsail": "Severne Mach 4  8.6",
    "sessionfin": "King Fins E5  44",
    "sessionurl": "https://www.gps-speedsurfing.com/?mnu=user&val=411777&uid=24908"
  },
  {
    "rowid": "18",
    "event_id": 810,
    "eventname": "2023 Odyssey of Speed",
    "speed": 32.4563,
    "type": "speed_halfhour",
    "username": "Sofia Koukouzeli",
    "ageclass": "Master (36-50)",
    "weightclass": "61-70",
    "sexe": "Woman",
    "spotname": "Loutsa",
    "sessionboard": "Fanatic Falcon TE 115",
    "sessionsail": "Neilpryde RS Racing EVO XIII  6.6",
    "sessionfin": "Custom Carpenter  35",
    "sessionurl": "https://www.gps-speedsurfing.com/?mnu=user&val=402794&uid=18072"
  },
  {
    "rowid": "19",
    "event_id": 810,
    "eventname": "2023 Odyssey of Speed",
    "speed": 31.89144,
    "type": "speed_halfhour",
    "username": "John John Vanderick",
    "ageclass": "Junior (11-14)",
    "weightclass": "41-50",
    "sexe": "Men",
    "spotname": "Kefalos, Kos",
    "sessionboard": "Starboard iSonic Reflex Carbon 67",
    "sessionsail": "Neilpryde RS Racing EVO XIV  6.5",
    "sessionfin": "iFins Nano Pure  32",
    "sessionurl": "https://www.gps-speedsurfing.com/?mnu=user&val=415311&uid=24571"
  },
  {
    "rowid": "20",
    "event_id": 810,
    "eventname": "2023 Odyssey of Speed",
    "speed": 30.870988000000004,
    "type": "speed_halfhour",
    "username": "Johan Huitema",
    "ageclass": "Super Master (61-70)",
    "weightclass": "81-90",
    "sexe": "Men",
    "spotname": "Karpathos",
    "sessionboard": "Starboard  iSonic 63 Carbon Reflex ",
    "sessionsail": "Neilpryde RS Racing EVO X  7.0",
    "sessionfin": "Sonntag Fins GPS 6  32",
    "sessionurl": "https://www.gps-speedsurfing.com/?mnu=user&val=418688&uid=4541"
  },
  {
    "rowid": "21",
    "event_id": 810,
    "eventname": "2023 Odyssey of Speed",
    "speed": 30.637636,
    "type": "speed_halfhour",
    "username": "Marco Lambers",
    "ageclass": "Master (36-50)",
    "weightclass": "91-100",
    "sexe": "Men",
    "spotname": "Karpathos",
    "sessionboard": "Starboard iSonic 63 Carbon Reflex",
    "sessionsail": "Severne Mach 6  6.5",
    "sessionfin": "Gasoil Fins CHR M  33",
    "sessionurl": "https://www.gps-speedsurfing.com/?mnu=user&val=415979&uid=22478"
  },
  {
    "rowid": "22",
    "event_id": 810,
    "eventname": "2023 Odyssey of Speed",
    "speed": 30.493180000000002,
    "type": "speed_halfhour",
    "username": "Giorgos Stogias",
    "ageclass": "Grand Master (51-60)",
    "weightclass": "91-100",
    "sexe": "Men",
    "spotname": "Schinias",
    "sessionboard": "Tabou Speedster 69 Ltd",
    "sessionsail": "Loft Sails racing blade  7.8",
    "sessionfin": "- Chopper ChC  36",
    "sessionurl": "https://www.gps-speedsurfing.com/?mnu=user&val=419555&uid=5658"
  },
  {
    "rowid": "23",
    "event_id": 810,
    "eventname": "2023 Odyssey of Speed",
    "speed": 29.626444000000003,
    "type": "speed_halfhour",
    "username": "Alexandros Grimpaviotis",
    "ageclass": "Master (36-50)",
    "weightclass": "71-80",
    "sexe": "Men",
    "spotname": "Chalkoutsi",
    "sessionboard": "FMX Invictus 124",
    "sessionsail": "Challenger Sails Bad 2  7.7",
    "sessionfin": "Z-fins SL -  41",
    "sessionurl": "https://www.gps-speedsurfing.com/?mnu=user&val=417636&uid=25595"
  },
  {
    "rowid": "24",
    "event_id": 810,
    "eventname": "2023 Odyssey of Speed",
    "speed": 29.624592000000003,
    "type": "speed_halfhour",
    "username": "Kostas Raptis",
    "ageclass": "Master (36-50)",
    "weightclass": "81-90",
    "sexe": "Men",
    "spotname": "Chalkoutsi",
    "sessionboard": "Starboard iSonic 72 Carbon Reflex ",
    "sessionsail": "Neilpryde RS Racing EVO XII  8.2",
    "sessionfin": "Z-fins ZSL S-  36",
    "sessionurl": "https://www.gps-speedsurfing.com/?mnu=user&val=417764&uid=2856"
  },
  {
    "rowid": "25",
    "event_id": 810,
    "eventname": "2023 Odyssey of Speed",
    "speed": 29.100476,
    "type": "speed_halfhour",
    "username": "Philip Adamidis",
    "ageclass": "Grand Master (51-60)",
    "weightclass": "91-100",
    "sexe": "Men",
    "spotname": "New Golden Beach",
    "sessionboard": "FMX Invictus 118",
    "sessionsail": "S2 Maui Venom  7.5",
    "sessionfin": "Z-fins SLM  36",
    "sessionurl": "https://www.gps-speedsurfing.com/?mnu=user&val=419533&uid=1608"
  },
  {
    "rowid": "26",
    "event_id": 810,
    "eventname": "2023 Odyssey of Speed",
    "speed": 28.737484000000002,
    "type": "speed_halfhour",
    "username": "Stephanos Grapsas",
    "ageclass": "Ultimate Master (71-99)",
    "weightclass": "61-70",
    "sexe": "Men",
    "spotname": "VALTOS",
    "sessionboard": "Starboard iSonic Carbon Reflex 97",
    "sessionsail": "Neilpryde EVO XIII  6.6",
    "sessionfin": "Z-fins SLM    35",
    "sessionurl": "https://www.gps-speedsurfing.com/?mnu=user&val=418039&uid=3182"
  },
  {
    "rowid": "27",
    "event_id": 810,
    "eventname": "2023 Odyssey of Speed",
    "speed": 28.359676000000004,
    "type": "speed_halfhour",
    "username": "Hannes Rieger",
    "ageclass": "Super Master (61-70)",
    "weightclass": "61-70",
    "sexe": "Men",
    "spotname": "Drepano",
    "sessionboard": "Custom FR 61/20",
    "sessionsail": "S2 Maui Wicked  6.3",
    "sessionfin": "Custom SL83  31",
    "sessionurl": "https://www.gps-speedsurfing.com/?mnu=user&val=412808&uid=24349"
  },
  {
    "rowid": "28",
    "event_id": 810,
    "eventname": "2023 Odyssey of Speed",
    "speed": 27.72444,
    "type": "speed_halfhour",
    "username": "Socrates Costicoglou",
    "ageclass": "Grand Master (51-60)",
    "weightclass": "71-80",
    "sexe": "Men",
    "spotname": "Schinias",
    "sessionboard": "Carbon Art SL99 Pro",
    "sessionsail": "Point-7 AC-1 2K18  7.8",
    "sessionfin": "Tectonics M2  36",
    "sessionurl": "https://www.gps-speedsurfing.com/?mnu=user&val=409476&uid=299"
  },
  {
    "rowid": "29",
    "event_id": 810,
    "eventname": "2023 Odyssey of Speed",
    "speed": 26.366924,
    "type": "speed_halfhour",
    "username": "Christos Psy",
    "ageclass": "Grand Master (51-60)",
    "weightclass": "81-90",
    "sexe": "Men",
    "spotname": "Chalkoutsi",
    "sessionboard": "FMX Invictus 118",
    "sessionsail": "Neilpryde RS Racing EVO XII  8.2",
    "sessionfin": "NoLo NoLo  38",
    "sessionurl": "https://www.gps-speedsurfing.com/?mnu=user&val=418478&uid=26975"
  },
  {
    "rowid": "30",
    "event_id": 810,
    "eventname": "2023 Odyssey of Speed",
    "speed": 26.303956,
    "type": "speed_halfhour",
    "username": "Konstantinos Palogos",
    "ageclass": "Grand Master (51-60)",
    "weightclass": "81-90",
    "sexe": "Men",
    "spotname": "Lefkanti",
    "sessionboard": "- Novenove International Corsa 90",
    "sessionsail": "S2 Maui Venom  5.7",
    "sessionfin": "Zulu Umbani  32",
    "sessionurl": "https://www.gps-speedsurfing.com/?mnu=user&val=416839&uid=23998"
  },
  {
    "rowid": "31",
    "event_id": 810,
    "eventname": "2023 Odyssey of Speed",
    "speed": 21.935088,
    "type": "speed_halfhour",
    "username": "Dirk Jan Knol",
    "ageclass": "Grand Master (51-60)",
    "weightclass": "91-100",
    "sexe": "Men",
    "spotname": "Karpathos",
    "sessionboard": "FMX Invictus 98",
    "sessionsail": "Challenger Sails Aero + 8  7.8",
    "sessionfin": "MS-Fins X6 S  32",
    "sessionurl": "https://www.gps-speedsurfing.com/?mnu=user&val=417865&uid=2035"
  },
  {
    "rowid": "32",
    "event_id": 810,
    "eventname": "2023 Odyssey of Speed",
    "speed": 20.601648,
    "type": "speed_halfhour",
    "username": "George Papagiannakis",
    "ageclass": "Grand Master (51-60)",
    "weightclass": "61-70",
    "sexe": "Men",
    "spotname": "VALTOS",
    "sessionboard": "Starboard Isonic 107 UltraCore Reflex Carbon",
    "sessionsail": "Loftsails RACING BLADE  7.8",
    "sessionfin": "F-Hot RWS-3  37",
    "sessionurl": "https://www.gps-speedsurfing.com/?mnu=user&val=416343&uid=6342"
  },
  {
    "rowid": "33",
    "event_id": 810,
    "eventname": "2023 Odyssey of Speed",
    "speed": 20.340516,
    "type": "speed_halfhour",
    "username": "Wouter van Hilst",
    "ageclass": "Master (36-50)",
    "weightclass": "91-100",
    "sexe": "Men",
    "spotname": "Karpathos",
    "sessionboard": "JP Slalom Pro 55",
    "sessionsail": "S2 Maui Venom  5.5",
    "sessionfin": "Sonntag Fins X4 RHF  255",
    "sessionurl": "https://www.gps-speedsurfing.com/?mnu=user&val=416809&uid=20700"
  },
  {
    "rowid": "34",
    "event_id": 810,
    "eventname": "2023 Odyssey of Speed",
    "speed": 17.990328,
    "type": "speed_halfhour",
    "username": "Mavris Haris",
    "ageclass": "Grand Master (51-60)",
    "weightclass": "81-90",
    "sexe": "Men",
    "spotname": "Anavissos",
    "sessionboard": "RRD X-Fire LTD V5 105",
    "sessionsail": "Point-7 AC1  7.1",
    "sessionfin": "iFins Nano Pure  36",
    "sessionurl": "https://www.gps-speedsurfing.com/?mnu=user&val=415238&uid=2117"
  },
  {
    "rowid": "35",
    "event_id": 810,
    "eventname": "2023 Odyssey of Speed",
    "speed": 13.062156,
    "type": "speed_halfhour",
    "username": "Antonis Giannopoulos",
    "ageclass": "Super Master (61-70)",
    "weightclass": "71-80",
    "sexe": "Men",
    "spotname": "Tsimari",
    "sessionboard": "PATRIK Speed 48",
    "sessionsail": "Loft Sails slalom  6.3",
    "sessionfin": "C3 SLINGSHOT  23",
    "sessionurl": "https://www.gps-speedsurfing.com/?mnu=user&val=404669&uid=6151"
  },
  {
    "rowid": "36",
    "event_id": 810,
    "eventname": "2023 Odyssey of Speed",
    "speed": 9.797080000000001,
    "type": "speed_halfhour",
    "username": "Sakellariou Kostas",
    "ageclass": "Grand Master (51-60)",
    "weightclass": "91-100",
    "sexe": "Men",
    "spotname": "Tsimari",
    "sessionboard": "PATRIK Speed 53",
    "sessionsail": "Sailloft Hamburg Ultimate  6.3",
    "sessionfin": "Gasoil Fins assy speed tribord  25",
    "sessionurl": "https://www.gps-speedsurfing.com/?mnu=user&val=416804&uid=4882"
  },
  {
    "rowid": "37",
    "event_id": 810,
    "eventname": "2023 Odyssey of Speed",
    "speed": 8.902564000000002,
    "type": "speed_halfhour",
    "username": "Thomopoulos Dinos",
    "ageclass": "Master (36-50)",
    "weightclass": "71-80",
    "sexe": "Men",
    "spotname": "Tsimari",
    "sessionboard": "Mistral speed 47",
    "sessionsail": "S2 Maui Venom  5.6",
    "sessionfin": "C3 SLINGSHOT  22",
    "sessionurl": "https://www.gps-speedsurfing.com/?mnu=user&val=404156&uid=1740"
  },
  {
    "rowid": "38",
    "event_id": 810,
    "eventname": "2023 Odyssey of Speed",
    "speed": 4.794828,
    "type": "speed_halfhour",
    "username": "Dionisis Papadatos",
    "ageclass": "Senior (19-35)",
    "weightclass": "101-110",
    "sexe": "Men",
    "spotname": "Drepano",
    "sessionboard": "Starboard iSonic 85 Carbon Reflex",
    "sessionsail": "S2 Maui Venom  7.6",
    "sessionfin": "Z-fins Z SLM S-  45",
    "sessionurl": "https://www.gps-speedsurfing.com/?mnu=user&val=404107&uid=23910"
  }
]